odoo/addons/purchase_security/README.rst
odoo/addons/purchase_security/__init__.py
odoo/addons/purchase_security/__manifest__.py
odoo/addons/purchase_security/i18n/es.po
odoo/addons/purchase_security/i18n/it.po
odoo/addons/purchase_security/i18n/pt_BR.po
odoo/addons/purchase_security/i18n/purchase_security.pot
odoo/addons/purchase_security/i18n/tr.po
odoo/addons/purchase_security/models/__init__.py
odoo/addons/purchase_security/models/ir_rule.py
odoo/addons/purchase_security/models/purchase_order.py
odoo/addons/purchase_security/models/purchase_team.py
odoo/addons/purchase_security/models/res_partner.py
odoo/addons/purchase_security/models/res_users.py
odoo/addons/purchase_security/readme/CONFIGURATION.rst
odoo/addons/purchase_security/readme/CONTRIBUTORS.md
odoo/addons/purchase_security/readme/DESCRIPTION.md
odoo/addons/purchase_security/readme/USAGE.md
odoo/addons/purchase_security/security/ir.model.access.csv
odoo/addons/purchase_security/security/security.xml
odoo/addons/purchase_security/static/description/icon.png
odoo/addons/purchase_security/static/description/index.html
odoo/addons/purchase_security/tests/__init__.py
odoo/addons/purchase_security/tests/test_access_rights.py
odoo/addons/purchase_security/views/purchase_order_views.xml
odoo/addons/purchase_security/views/purchase_team_views.xml
odoo/addons/purchase_security/views/res_partner_views.xml
odoo_addon_purchase_security-18.0.1.1.0.5.dist-info/METADATA
odoo_addon_purchase_security-18.0.1.1.0.5.dist-info/WHEEL
odoo_addon_purchase_security-18.0.1.1.0.5.dist-info/top_level.txt
odoo_addon_purchase_security-18.0.1.1.0.5.dist-info/RECORD
